Metadata-Version: 2.1
Name: hopperlib
Version: 0.0.1
Summary: hopperlib is a joke/troll library that I created. This library is a complete joke and should not be taken seriously.
Home-page: UNKNOWN
Author: CULT
Author-email: 010101cool@gmail.com
License: MIT
Keywords: hopperlib
Platform: UNKNOWN
Classifier: Development Status :: 5 - Production/Stable
Classifier: Intended Audience :: Education
Classifier: Operating System :: Microsoft :: Windows :: Windows 10
Classifier: License :: OSI Approved :: MIT License
Classifier: Programming Language :: Python :: 3
License-File: LICENCE.txt
